crslab/__init__.py
crslab/download.py
crslab/config/__init__.py
crslab/config/config.py
crslab/data/__init__.py
crslab/data/dataloader/__init__.py
crslab/data/dataloader/base.py
crslab/data/dataloader/inspired.py
crslab/data/dataloader/kbrd.py
crslab/data/dataloader/kgsf.py
crslab/data/dataloader/redial.py
crslab/data/dataloader/tgredial.py
crslab/data/dataloader/utils.py
crslab/data/dataset/__init__.py
crslab/data/dataset/base.py
crslab/data/dataset/durecdial/__init__.py
crslab/data/dataset/durecdial/durecdial.py
crslab/data/dataset/durecdial/resources.py
crslab/data/dataset/gorecdial/__init__.py
crslab/data/dataset/gorecdial/gorecdial.py
crslab/data/dataset/gorecdial/resources.py
crslab/data/dataset/inspired/__init__.py
crslab/data/dataset/inspired/inspired.py
crslab/data/dataset/inspired/resources.py
crslab/data/dataset/opendialkg/__init__.py
crslab/data/dataset/opendialkg/opendialkg.py
crslab/data/dataset/opendialkg/resources.py
crslab/data/dataset/redial/__init__.py
crslab/data/dataset/redial/redial.py
crslab/data/dataset/redial/resources.py
crslab/data/dataset/tgredial/__init__.py
crslab/data/dataset/tgredial/resources.py
crslab/data/dataset/tgredial/tgredial.py
crslab/evaluator/__init__.py
crslab/evaluator/base.py
crslab/evaluator/conv.py
crslab/evaluator/embeddings.py
crslab/evaluator/end2end.py
crslab/evaluator/rec.py
crslab/evaluator/standard.py
crslab/evaluator/utils.py
crslab/evaluator/metrics/__init__.py
crslab/evaluator/metrics/base.py
crslab/evaluator/metrics/gen.py
crslab/evaluator/metrics/rec.py
crslab/model/__init__.py
crslab/model/base.py
crslab/model/pretrained_models.py
crslab/model/conversation/__init__.py
crslab/model/conversation/gpt2/__init__.py
crslab/model/conversation/gpt2/gpt2.py
crslab/model/conversation/transformer/__init__.py
crslab/model/conversation/transformer/transformer.py
crslab/model/crs/__init__.py
crslab/model/crs/inspired/__init__.py
crslab/model/crs/inspired/inspired_conv.py
crslab/model/crs/inspired/inspired_rec.py
crslab-0.1.2.dist-info/LICENSE
crslab-0.1.2.dist-info/METADATA
crslab-0.1.2.dist-info/WHEEL
crslab-0.1.2.dist-info/top_level.txt
crslab-0.1.2.dist-info/RECORD
