Metadata-Version: 2.1
Name: crslab
Version: 0.1.2
Summary: An Open-Source Toolkit for Building Conversational Recommender System(CRS)
Home-page: https://github.com/RUCAIBox/CRSLab
Author: CRSLabTeam
Author-email: francis_kun_zhou@163.com
License: UNKNOWN
Platform: UNKNOWN
Classifier: Programming Language :: Python :: 3
Classifier: License :: OSI Approved :: MIT License
Classifier: Topic :: Scientific/Engineering :: Artificial Intelligence
Classifier: Topic :: Scientific/Engineering :: Human Machine Interfaces
Requires-Python: >=3.6
Requires-Dist: numpy (~=1.19.4)
Requires-Dist: transformers (~=4.4.2)
Requires-Dist: fasttext (~=0.9.2)
Requires-Dist: pkuseg (~=0.0.25)
Requires-Dist: pyyaml (~=5.4)
Requires-Dist: tqdm (~=4.55.0)
Requires-Dist: loguru (~=0.5.3)
Requires-Dist: nltk (~=3.4.4)
Requires-Dist: requests (~=2.25.1)
Requires-Dist: scikit-learn (~=0.24.0)
Requires-Dist: fuzzywuzzy (~=0.18.0)
Requires-Dist: tensorboard (~=2.4.1)
Requires-Dist: dataclasses (~=0.7) ; python_version < "3.7"
